README.md
setup.py
coffeewhale/__init__.py
coffeewhale/coffeewhale.py
coffeewhale.egg-info/PKG-INFO
coffeewhale.egg-info/SOURCES.txt
coffeewhale.egg-info/dependency_links.txt
coffeewhale.egg-info/requires.txt
coffeewhale.egg-info/top_level.txt