Metadata-Version: 1.0
Name: coffeewhale
Version: 0.0.17
Summary: coffeewhale, a whale that tells you the job is done, when it's done!
Home-page: https://github.com/hongkunyoo/coffeewhale
Author: Hongkun Yoo
Author-email: hongkunyoo@gmail.com
License: MIT License
Keywords: slack api,slack notification
Platform: UNKNOWN
